<?xml version="1.0" encoding="UTF-8"?>
<Deal portal_deal_id="759" application_group="BSS and EWCS" revision_id="4156" action_name="NewDeal" action_code="001" message_type="A"><General_information><Deal_name><![CDATA[Tuesday 13/06/2017 Name]]></Deal_name><Bank_deal_id><![CDATA[Tuesday 13/06/2017]]></Bank_deal_id></General_information><Application_route>Non-ATP</Application_route><Application_owner>audrius.vaitonis+bank@ukexportfinance.gov.uk</Application_owner><Application_owner_email>audrius.vaitonis+bank@ukexportfinance.gov.uk</Application_owner_email><Application_bank>First Bank</Application_bank><UKEF_deal_id/><Deal_information><Exporter_and_indemnifier><Customer_type>1</Customer_type><Exporter_co_hse_reg_number>00000006</Exporter_co_hse_reg_number><Exporter_registration_source>Companies House</Exporter_registration_source><Exporter_name><![CDATA[LS KANSAS SIX LLP]]></Exporter_name><Exporter_postcode>W1F 0UT</Exporter_postcode><Industry_sector_code>48</Industry_sector_code><Industry_sector_name>48</Industry_sector_name><Industry_class_code>4813</Industry_class_code><Industry_class_name>4813</Industry_class_name><Sme_type>1</Sme_type><Description_of_export><![CDATA[Description of export]]></Description_of_export><Bank_security/><Indemnifier_co_hse_reg_number>00000006</Indemnifier_co_hse_reg_number><Indemnifier_name><![CDATA[LS KANSAS SIX LLP]]></Indemnifier_name><Indemnifier_postcode>W1F 0UT</Indemnifier_postcode></Exporter_and_indemnifier><Buyer><Buyer_name><![CDATA[Buyer name 11]]></Buyer_name><Buyer_country_code>24</Buyer_country_code><Buyer_country_name>Angola</Buyer_country_name><Destination_country_code>660</Destination_country_code><Destination_country_label>Anguilla</Destination_country_label></Buyer><Financial><Deal_currency_code>2</Deal_currency_code><Deal_currency_name>AUD - Australian Dollars</Deal_currency_name><Conversion_rate>1.12</Conversion_rate><Conversion_date>13-06-2017</Conversion_date><Contract_value>3000.00</Contract_value></Financial></Deal_information><Eligibility_checklist><Ec_agents_check>true</Ec_agents_check><Ec_initial_term_check>true</Ec_initial_term_check><Ec_total_exposure_check>true</Ec_total_exposure_check><Ec_bond_issuance_check>true</Ec_bond_issuance_check><Ec_industry_check>true</Ec_industry_check><Ec_indemnifier_turnover_check>true</Ec_indemnifier_turnover_check><Ec_indemnifier_net_worth_check>true</Ec_indemnifier_net_worth_check><Ec_indemnifier_liquidity_check>true</Ec_indemnifier_liquidity_check><Ec_indemnifier_filed_accounts_check>true</Ec_indemnifier_filed_accounts_check><Ec_indemnifier_watchlist_check>true</Ec_indemnifier_watchlist_check><Ec_indemnifier_rating_check>true</Ec_indemnifier_rating_check><Ec_internal_approval_check>true</Ec_internal_approval_check><Ec_third_party_check xmlns:xsi="http://www.w3.org/2001/XMLSchema-instance" xsi:nil="true"/><Agent_name/><Agent_address/></Eligibility_checklist><Facilities><BSS><UKEF_BSS_facility_id/><BSS_Guarantee_details><BSS_portal_facility_id>4432</BSS_portal_facility_id><BSS_bank_id/><BSS_issuer><![CDATA[Bond issuer 11]]></BSS_issuer><BSS_type>2</BSS_type><BSS_stage>2</BSS_stage><BSS_beneficiary><![CDATA[Bond beneficiary Name]]></BSS_beneficiary></BSS_Guarantee_details><BSS_Financial_details><BSS_value>20000.00</BSS_value><BSS_currency_code>2</BSS_currency_code><BSS_currency_name>AUD - Australian Dollars</BSS_currency_name><BSS_conversion_rate_deal>1.12</BSS_conversion_rate_deal><BSS_conversion_date_deal>13-06-2017</BSS_conversion_date_deal><BSS_fee_rate>10</BSS_fee_rate><BSS_fee_perc>9.0000</BSS_fee_perc><BSS_guarantee_perc>5</BSS_guarantee_perc><BSS_max_liability>1000.00</BSS_max_liability><BSS_min_quarterly_fee>1000</BSS_min_quarterly_fee></BSS_Financial_details><BSS_Dates_repayments><BSS_premium_freq>1</BSS_premium_freq><BSS_premium_type>1</BSS_premium_type><BSS_commitment_date>13-06-2017</BSS_commitment_date><BSS_issue_date/><BSS_guarantee_expiry_date>13-06-2020</BSS_guarantee_expiry_date><BSS_exposure_period>36</BSS_exposure_period><BSS_day_basis>1</BSS_day_basis></BSS_Dates_repayments></BSS><BSS><UKEF_BSS_facility_id/><BSS_Guarantee_details><BSS_portal_facility_id>4433</BSS_portal_facility_id><BSS_bank_id/><BSS_issuer><![CDATA[Bond issuer 22]]></BSS_issuer><BSS_type>3</BSS_type><BSS_stage>2</BSS_stage><BSS_beneficiary><![CDATA[Bond beneficiary name]]></BSS_beneficiary></BSS_Guarantee_details><BSS_Financial_details><BSS_value>20000.00</BSS_value><BSS_currency_code>2</BSS_currency_code><BSS_currency_name>AUD - Australian Dollars</BSS_currency_name><BSS_conversion_rate_deal>1.12</BSS_conversion_rate_deal><BSS_conversion_date_deal>13-06-2017</BSS_conversion_date_deal><BSS_fee_rate>10</BSS_fee_rate><BSS_fee_perc>9.0000</BSS_fee_perc><BSS_guarantee_perc>10</BSS_guarantee_perc><BSS_max_liability>2000.00</BSS_max_liability><BSS_min_quarterly_fee>100</BSS_min_quarterly_fee></BSS_Financial_details><BSS_Dates_repayments><BSS_premium_freq>1</BSS_premium_freq><BSS_premium_type>1</BSS_premium_type><BSS_commitment_date>14-06-2017</BSS_commitment_date><BSS_issue_date/><BSS_guarantee_expiry_date>14-06-2018</BSS_guarantee_expiry_date><BSS_exposure_period>10</BSS_exposure_period><BSS_day_basis>1</BSS_day_basis></BSS_Dates_repayments></BSS><EWCS><UKEF_EWCS_facility_id/><EWCS_Guarantee_details><EWCS_portal_facility_id>4434</EWCS_portal_facility_id><EWCS_bank_id>Bank facility number 08934</EWCS_bank_id><EWCS_stage>2</EWCS_stage></EWCS_Guarantee_details><EWCS_Financial_details><EWCS_value>10.50</EWCS_value><EWCS_currency_code>2</EWCS_currency_code><EWCS_currency_name>AUD - Australian Dollars</EWCS_currency_name><EWCS_conversion_rate_deal>1.12</EWCS_conversion_rate_deal><EWCS_conversion_date_deal>13-06-2017</EWCS_conversion_date_deal><EWCS_interest_rate>5</EWCS_interest_rate><EWCS_fee_perc>4.5000</EWCS_fee_perc><EWCS_guarantee_perc>2</EWCS_guarantee_perc><EWCS_max_liability>0.21</EWCS_max_liability><EWCS_min_quarterly_fee>100</EWCS_min_quarterly_fee></EWCS_Financial_details><EWCS_Dates_repayments><EWCS_premium_freq>1</EWCS_premium_freq><EWCS_premium_type>1</EWCS_premium_type><EWCS_commitment_date>20-06-2017</EWCS_commitment_date><EWCS_issue_date/><EWCS_guarantee_expiry_date>20-06-2018</EWCS_guarantee_expiry_date><EWCS_exposure_period>10</EWCS_exposure_period><EWCS_day_basis>1</EWCS_day_basis></EWCS_Dates_repayments><EWCS_Drawdowns><EWCS_Drawdown_details><EWCS_drawdown_date>20-06-2017</EWCS_drawdown_date><EWCS_drawdown_amount>10.00</EWCS_drawdown_amount><EWCS_drawdown_cumulative>500.00</EWCS_drawdown_cumulative></EWCS_Drawdown_details></EWCS_Drawdowns></EWCS></Facilities><Deal_summary><Deal_no_facilities>3</Deal_no_facilities><Deal_total_exposure_gbp>3360.24</Deal_total_exposure_gbp><Deal_total_premium_gbp>280.00</Deal_total_premium_gbp><Deal_total_exposure_deal_cur>3000.21</Deal_total_exposure_deal_cur><Deal_total_premium_deal_cur>250.00</Deal_total_premium_deal_cur><BSS_no_facilities>2</BSS_no_facilities><BSS_total_exposure_gbp>3360.00</BSS_total_exposure_gbp><BSS_total_premium_gbp>280.00</BSS_total_premium_gbp><BSS_total_exposure_deal_cur>3000.00</BSS_total_exposure_deal_cur><BSS_total_premium_deal_cur>250.00</BSS_total_premium_deal_cur><EWCS_no_facilities>1</EWCS_no_facilities><EWCS_total_exposure_gbp>0.24</EWCS_total_exposure_gbp><EWCS_total_premium_gbp>0.00</EWCS_total_premium_gbp><EWCS_total_exposure_deal_cur>0.21</EWCS_total_exposure_deal_cur><EWCS_total_premium_deal_cur>0.00</EWCS_total_premium_deal_cur></Deal_summary><Deal_files/></Deal>
